lambada/__init__.py
lambada/cli.py
lambada/models.py
lambada_again-0.2.6.dist-info/LICENSE
lambada_again-0.2.6.dist-info/METADATA
lambada_again-0.2.6.dist-info/WHEEL
lambada_again-0.2.6.dist-info/entry_points.txt
lambada_again-0.2.6.dist-info/top_level.txt
lambada_again-0.2.6.dist-info/RECORD
